infra_surveyor/__init__.py
infra_surveyor/_version.py
infra_surveyor/commands.py
infra_surveyor/graphing.py
infra_surveyor/icons.py
infra_surveyor/cloud/__init__.py
infra_surveyor/cloud/models.py
infra_surveyor/cloud/aws/__init__.py
infra_surveyor/cloud/aws/boto_utilities.py
infra_surveyor/cloud/aws/event_rules.py
infra_surveyor/cloud/aws/lambda_functions.py
infra_surveyor/cloud/aws/sns_topics.py
infra_surveyor/cloud/aws/sqs_queues.py
infra_surveyor-0.6.0.dist-info/entry_points.txt
infra_surveyor-0.6.0.dist-info/LICENSE
infra_surveyor-0.6.0.dist-info/WHEEL
infra_surveyor-0.6.0.dist-info/METADATA
infra_surveyor-0.6.0.dist-info/RECORD
