Metadata-Version: 2.1
Name: infra_surveyor
Version: 0.6.0
Summary: An Autodocumenting tool for Cloud Infrastructure
Keywords: AWS,Cloud,Documentation,Architecture
Classifier: Programming Language :: Python :: 3
Classifier: License :: OSI Approved :: BSD License
Classifier: Operating System :: OS Independent
Requires-Dist: click
Requires-Dist: awscrt
Requires-Dist: boto3[crt]
Requires-Dist: graphviz
Requires-Dist: moto[all] ; extra == "dev"
Requires-Dist: docker ; extra == "dev"
Requires-Dist: coverage[toml] ; extra == "dev"
Requires-Dist: pytest-cov ; extra == "dev"
Requires-Dist: black ; extra == "dev"
Requires-Dist: python-semantic-release ; extra == "dev"
Requires-Dist: mkdocs==1.3.0 ; extra == "docs"
Requires-Dist: mkdocs-redirects==1.0.1 ; extra == "docs"
Requires-Dist: jinja2==3.0.3 ; extra == "docs"
Requires-Dist: flit ; extra == "release"
Project-URL: Documentation, https://infrasurveyor.readthedocs.io/en/latest/
Project-URL: Source, https://github.com/DavidWylie/InfraSurveyor
Provides-Extra: dev
Provides-Extra: docs
Provides-Extra: release
